PanoFF_Excel/PanoFF_Excel.py
PanoFF_Excel/__init__.py
PanoFF_Excel-0.3.dist-info/METADATA
PanoFF_Excel-0.3.dist-info/WHEEL
PanoFF_Excel-0.3.dist-info/top_level.txt
PanoFF_Excel-0.3.dist-info/RECORD
