Metadata-Version: 2.1
Name: PanoFF_Excel
Version: 0.3
Summary: Егэ 22 задание. Авто заполнение таблицы. Шаблонный алгоритм.
Author: S4CBS
Author-email: aap200789@gmail.com
Classifier: Programming Language :: Python :: 3
Classifier: License :: OSI Approved :: MIT License
Classifier: Operating System :: OS Independent
Requires-Python: >=3.6
Requires-Dist: openpyxl
Requires-Dist: xlrd
